CHANGELOG.txt
LICENSE.txt
MANIFEST.in
README.txt
ejemplo_cfdi.py
setup.py
cfdi_utils/CFDI40.py
cfdi_utils/SelloDigital.py
cfdi_utils/__init__.py
cfdi_utils.egg-info/PKG-INFO
cfdi_utils.egg-info/SOURCES.txt
cfdi_utils.egg-info/dependency_links.txt
cfdi_utils.egg-info/requires.txt
cfdi_utils.egg-info/top_level.txt
support-files/CFDI40.py
support-files/CFDI40_sub.py
support-files/SelloDigital.py
support-files/dev-log.txt