Metadata-Version: 2.1
Name: cfdi-utils
Version: 0.0.2
Summary: Utilities to work with CFDI
Home-page: 
Author: Arturo Castillo
Author-email: arturguay@gmail.com
License: MIT
Keywords: cfdi
Platform: UNKNOWN
Classifier: Development Status :: 3 - Alpha
Classifier: Intended Audience :: Developers
Classifier: License :: OSI Approved :: MIT License
Classifier: Programming Language :: Python :: 3
Classifier: Topic :: Software Development :: Libraries :: Python Modules
License-File: LICENSE.txt
